README
setup.cfg
setup.py
the_ends/EquationErrorCheck.py
the_ends/EquationObject.py
the_ends/RunAndOutput.py
the_ends/Solver.py
the_ends/__init__.py
the_ends/__main__.py
the_ends/readfile.py
the_ends/scipy_solver.py
the_ends/tmp.py
the_ends.egg-info/PKG-INFO
the_ends.egg-info/SOURCES.txt
the_ends.egg-info/dependency_links.txt
the_ends.egg-info/entry_points.txt
the_ends.egg-info/top_level.txt