Metadata-Version: 1.1
Name: the-ends
Version: 0.1.7
Summary: Implicit Equation Solver (will reorder equations for maths)
Home-page: https://github.com/Kevincavender/the_ends
Author: Kevin Cavender
Author-email: kac1200@gmail.com
License: UNKNOWN
Download-URL: https://github.com/Kevincavender/the_ends/archive/0.1.tar.gz
Keywords: equation,engineer,math,calculator
Platform: UNKNOWN
